datafakegenerator/__init__.py
datafakegenerator/base_generator.py
datafakegenerator/data_fake_generator.py
datafakegenerator/dataset_manager.py
datafakegenerator/exporters.py
datafakegenerator/provider_factory.py
datafakegenerator/external_datasets/csv/ICD10_diagnosis.csv
datafakegenerator/external_datasets/csv/ICD10_procedure.csv
datafakegenerator/external_datasets/csv/ICD9_diagnosis.csv
datafakegenerator/external_datasets/csv/ICD9_procedure.csv
datafakegenerator/external_datasets/csv/airlines.csv
datafakegenerator/external_datasets/csv/airport.csv
datafakegenerator/external_datasets/csv/animals.csv
datafakegenerator/external_datasets/csv/app.csv
datafakegenerator/external_datasets/csv/athlete.csv
datafakegenerator/external_datasets/csv/bank.csv
datafakegenerator/external_datasets/csv/books.csv
datafakegenerator/external_datasets/csv/cars.csv
datafakegenerator/external_datasets/csv/colors.csv
datafakegenerator/external_datasets/csv/company.csv
datafakegenerator/external_datasets/csv/construction_code.csv
datafakegenerator/external_datasets/csv/countries.csv
datafakegenerator/external_datasets/csv/cryptocurrency.csv
datafakegenerator/external_datasets/csv/css_class.csv
datafakegenerator/external_datasets/csv/drugs.csv
datafakegenerator/external_datasets/csv/hcpcs.csv
datafakegenerator/external_datasets/csv/hospital.csv
datafakegenerator/external_datasets/csv/language.csv
datafakegenerator/external_datasets/csv/movies.csv
datafakegenerator/external_datasets/csv/noise.csv
datafakegenerator/external_datasets/csv/period_table.csv
datafakegenerator/external_datasets/csv/plants.csv
datafakegenerator/external_datasets/csv/product.csv
datafakegenerator/external_datasets/csv/slogan.csv
datafakegenerator/external_datasets/csv/states.csv
datafakegenerator/external_datasets/csv/stocks.csv
datafakegenerator/external_datasets/csv/university.csv
datafakegenerator/external_datasets/csv/video_games.csv
datafakegenerator/external_datasets/csv/words.csv
datafakegenerator-1.2.2.dist-info/licenses/LICENSE
datafakegenerator-1.2.2.dist-info/METADATA
datafakegenerator-1.2.2.dist-info/WHEEL
datafakegenerator-1.2.2.dist-info/top_level.txt
datafakegenerator-1.2.2.dist-info/RECORD
