Metadata-Version: 2.4
Name: datafakegenerator
Version: 1.2.2
Summary: A powerful, flexible Python library for generating realistic fake data across 700+ data types with multi-format export capabilities.
Home-page: https://github.com/ikigamisama/DataFakeGenerator
Author: Franz Monzales
Author-email: ikigamidevs@gmail.com
Classifier: Programming Language :: Python :: 3
Classifier: License :: OSI Approved :: MIT License
Classifier: Operating System :: OS Independent
Requires-Python: >=3.8
License-File: LICENSE
Dynamic: license-file
